setup.py
restpager/__init__.py
restpager/args.py
restpager/pager.py
restpager.egg-info/PKG-INFO
restpager.egg-info/SOURCES.txt
restpager.egg-info/dependency_links.txt
restpager.egg-info/namespace_packages.txt
restpager.egg-info/not-zip-safe
restpager.egg-info/requires.txt
restpager.egg-info/top_level.txt