Metadata-Version: 1.1
Name: restpager
Version: 0.1
Summary: A RESTful pager class for Flask
Home-page: http://github.com/pudo/restpager
Author: Friedrich Lindenberg
Author-email: friedrich@pudo.org
License: MIT
Platform: any
Classifier: Development Status :: 4 - Beta
Classifier: Environment :: Web Environment
Classifier: Intended Audience :: Developers
Classifier: License :: OSI Approved :: BSD License
Classifier: Operating System :: OS Independent
Classifier: Programming Language :: Python
Classifier: Topic :: Internet :: WWW/HTTP :: Dynamic Content
Classifier: Topic :: Software Development :: Libraries :: Python Modules
